vecto/__init__.py
vecto/__main__.py
vecto/_version.py
vecto/cli.py
vecto/config.py
vecto/benchmarks/__init__.py
vecto/benchmarks/base.py
vecto/benchmarks/visualize.py
vecto/benchmarks/analogy/__init__.py
vecto/benchmarks/analogy/analogy.py
vecto/benchmarks/analogy/io.py
vecto/benchmarks/analogy/solvers.py
vecto/benchmarks/categorization/__init__.py
vecto/benchmarks/categorization/categorization.py
vecto/benchmarks/categorization/metrics.py
vecto/benchmarks/language_modeling/__init__.py
vecto/benchmarks/language_modeling/language_modeling.py
vecto/benchmarks/outliers/__init__.py
vecto/benchmarks/outliers/__main__.py
vecto/benchmarks/outliers/outliers.py
vecto/benchmarks/relation_extraction/__init__.py
vecto/benchmarks/relation_extraction/preprocess.py
vecto/benchmarks/relation_extraction/relation_extraction.py
vecto/benchmarks/sequence_labeling/__init__.py
vecto/benchmarks/sequence_labeling/sequence_labeling.py
vecto/benchmarks/similarity/__init__.py
vecto/benchmarks/similarity/similarity.py
vecto/benchmarks/synonymy_detection/__init__.py
vecto/benchmarks/synonymy_detection/__main__.py
vecto/benchmarks/synonymy_detection/synonymy_detection.py
vecto/benchmarks/text_classification/__init__.py
vecto/benchmarks/text_classification/nets.py
vecto/benchmarks/text_classification/nlp_utils.py
vecto/benchmarks/text_classification/text_classification.py
vecto/benchmarks/text_classification/text_datasets.py
vecto/corpus/__init__.py
vecto/corpus/base.py
vecto/corpus/corpus.py
vecto/corpus/iterators.py
vecto/corpus/preprocess.py
vecto/corpus/tokenization.py
vecto/data/__init__.py
vecto/data/base.py
vecto/data/io.py
vecto/embeddings/__init__.py
vecto/embeddings/base.py
vecto/embeddings/dense.py
vecto/embeddings/legacy_w2v.py
vecto/embeddings/train_word2vec.py
vecto/embeddings/utils/__init__.py
vecto/embeddings/utils/subword.py
vecto/embeddings/utils/word.py
vecto/utils/__init__.py
vecto/utils/blas.py
vecto/utils/convert.py
vecto/utils/data.py
vecto/utils/fetch_benchmarks.py
vecto-0.2.21.dist-info/LICENSE
vecto-0.2.21.dist-info/METADATA
vecto-0.2.21.dist-info/WHEEL
vecto-0.2.21.dist-info/top_level.txt
vecto-0.2.21.dist-info/RECORD
