Metadata-Version: 2.1
Name: vecto
Version: 0.2.21
Summary: toolbox for various tasks in the area of vector space models of computational linguistic
Home-page: http://vecto.space
Author: 
Author-email: 
Maintainer: 
Maintainer-email: 
License: Apache License 2.0
Keywords: NLP,linguistics,language
Platform: UNKNOWN
Classifier: Development Status :: 3 - Alpha
Classifier: Environment :: Console
Classifier: Intended Audience :: Science/Research
Classifier: License :: OSI Approved :: Apache Software License
Classifier: Natural Language :: English
Classifier: Operating System :: POSIX
Classifier: Programming Language :: Python :: 3.5
Classifier: Programming Language :: Python :: 3.6
Classifier: Programming Language :: Python :: 3 :: Only
Classifier: Topic :: Text Processing :: Linguistic
Requires-Python: >=3.5
License-File: LICENSE
Requires-Dist: brewer2mpl
Requires-Dist: numpy
Requires-Dist: nltk
Requires-Dist: pandas
Requires-Dist: progressbar2
Requires-Dist: matplotlib
Requires-Dist: scipy
Requires-Dist: scikit-learn
Requires-Dist: system-query
Requires-Dist: tables
Requires-Dist: traitlets
Requires-Dist: tqdm
Requires-Dist: requests
